{
  "message_id": "137157",
  "channel": "sut_tw",
  "channel_url": "https://t.me/s/sut_tw",
  "content": "چین و هند چجوری هیچوقت تو جام جهانی ها نیستن؟   \nیعنی بین اون یه میلیارد نفر ۱۱ نفر نیستن بتونن فوتبال بازی کنن جاکشا؟  \n  \n[#جام_جهانی](?q=%23%D8%AC%D8%A7%D9%85_%D8%AC%D9%87%D8%A7%D9%86%DB%8C)  \n  \n^Kasra^  \n  \n[@sut_tw](https://t.me/sut_tw)",
  "timestamp": "17:49",
  "photo_url": null,
  "photo_count": 0,
  "video_url": null,
  "video_thumb_url": null,
  "audio_url": null,
  "document_url": null,
  "document_filename": null,
  "document_description": null,
  "telegram_post_link": null,
  "downloaded_media": [],
  "fetched_at": "2026-06-18T14:29:01Z"
}