{
  "id": "337868",
  "channel": "IranintlTV",
  "channel_url": "https://t.me/s/IranintlTV",
  "text": "روزنامه گاردین در گزارشی با طرح این پرسش که آیا جمهوری اسلامی می‌تواند برای کابل‌های زیردریایی در تنگه هرمز عوارض دریافت کند، نوشت تحقق این موضوع بسیار بعید است. یک مقام پیشین آمریکایی گفت این کابل‌ها از ساحل بسیار دور هستند و ایران فناوری لازم برای قطع کردن آنها را ندارد.این گزارش به نقل از یک مقام سابق وزارت خارجه آمریکا که متخصص اینترنت جهانی است، همچنین نوشت: ‌«دریافت هزینه از شرکت‌های خاص غیرممکن خواهد بود، زیرا هیچ راهی برای تفکیک ترافیک اینترنت آنها وجود ندارد.»این مقام آمریکایی همچنین گفت: «بسیار بعید است که ایران بتواند کابل‌های زیر تنگه هرمز را بدون جلب توجه قطع کند؛ این کشور فناوری لازم را ندارد و باید این کار را آشکارا و تحت نظارت مداوم گشت‌های هوایی ایالات متحده انجام دهد.»طبق این گزارش، دست‌کم هفت کابل در زیر آب‌های این تنگه قرار دارند که بسیاری از آنها برای توسعه هوش مصنوعی در کشورهای خلیج فارس حیاتی هستند.https://iranintl.com/202605198606",
  "timestamp": "2026-05-19T02:54:36+00:00",
  "media": [
    {
      "type": "photo",
      "filename": "337868_photo_0.jpg",
      "size": 73997
    }
  ],
  "fetched_at": "2026-05-19T06:11:26.618325"
}