{
  "id": "337877",
  "channel": "IranintlTV",
  "channel_url": "https://t.me/s/IranintlTV",
  "text": "لیندزی گراهام، سناتور جمهوری‌خواه، تاکید کرد: «خط پایانی برای مذاکرات با جمهوری اسلامی و رسیدن به توافق وجود ندارد، زیرا حکومت ایران هر روز این خط پایان را تغییر می‌دهد.»جزییات بیشتر با مرضیه حسینی، خبرنگار ایران‌اینترنشنال@iranintltv",
  "timestamp": null,
  "media": [
    {
      "type": "video",
      "filename": "337877_video.mp4",
      "size": 1301336
    }
  ],
  "fetched_at": "2026-05-19T06:11:42.315791"
}