{
  "id": "298610",
  "channel": "VahidHeadline",
  "channel_url": "https://t.me/s/VahidHeadline",
  "text": "‌ ‌ ‌ ‌ ساختمان اداری با پنجره‌های شیشه‌ای که بالای یک فروشگاه رامن در قلب محله چینی‌های منهتن قرار داشت، در میان خیابانی شلوغ از رستوران‌های چینی، فروشگاه‌های مواد غذایی و آپارتمان‌ها، ظاهری عادی و بدون ‌جلب ‌توجه داشت.در سال ۲۰۲۲، لو جیان‌وانگ، رئیس ۶۴ ساله یک گروه اجتماعی چینی، در یکی از طبقات آنجا دفتر گرفت و فضایی ایجاد کرد که به گفته وکلایش قرار بود به مهاجران برای تمدید گواهینامه رانندگی کمک کند و همچنین محلی برای بازی پینگ‌پنگ روی میزی در اتاق کنفرانس باشد.اما مدت زیادی نگذشت که اف‌بی‌آی، پلیس فدرال آمریکا، به این محل یورش برد و آقای لو را متهم کرد که به دستور دولت چین نخستین ایستگاه پلیس برون‌مرزی شناخته‌شده در آمریکا را ایجاد کرده است.او تنها چند روز پس از آنکه یک سیاستمدار کالیفرنیا نیز به جرایم مشابه اعتراف کرد، به جرم فعالیت به‌عنوان مامور خارجی ثبت‌نشده برای چین مجرم شناخته شد.bbc.in📸GettyImages/ Reuters‌🇬🇧 BBCPersian🤖 @VahidHeadline",
  "timestamp": "2026-05-19T04:34:05+00:00",
  "media": [
    {
      "type": "photo",
      "filename": "298610_photo_0.jpg",
      "size": 96150
    },
    {
      "type": "photo",
      "filename": "298610_photo_1.jpg",
      "size": 89394
    },
    {
      "type": "photo",
      "filename": "298610_photo_2.jpg",
      "size": 111051
    },
    {
      "type": "photo",
      "filename": "298610_photo_3.jpg",
      "size": 98381
    },
    {
      "type": "photo",
      "filename": "298610_photo_4.jpg",
      "size": 104052
    }
  ],
  "fetched_at": "2026-05-19T06:11:50.270462"
}