{
  "message_id": "138389",
  "channel": "sut_tw",
  "channel_url": "https://t.me/s/sut_tw",
  "content": "> تجربه های کانادا\n> تجربه ویزا کانادا\n> 🇨🇦\n> وضعیت فاند:  partially-funded . دانشگاه مقصد: Ontario Tech University  . دپارتمان/رشته:  Engineering Management . مقطع پذیرش:  Master of engineering management . دانشگاه مبدا:  علم و صنعت معدل لیسانس:  17.11 . معدل ارشد:  17.32 . معدل…\n\nکاش یکی اینجوری پیدا میشد منو میذاش تو چمدون با خودش میبرد...",
  "timestamp": "23:07",
  "photo_url": null,
  "photo_count": 0,
  "video_url": null,
  "video_thumb_url": null,
  "audio_url": null,
  "document_url": null,
  "document_filename": null,
  "document_description": null,
  "telegram_post_link": null,
  "downloaded_media": [],
  "fetched_at": "2026-06-30T19:39:01Z"
}