{
  "message_id": "719335",
  "channel": "PriceNerd",
  "channel_url": "https://t.me/s/PriceNerd",
  "content": "🛢 نفت خام: **72.9$** | **دلار: 180,631 تومان**  \n  \n🕰 بروزرسانی - 18 تیر 1405 - 12:19  \n  \n**🪙قیمت لحظه ای رمز ارزهای پرمخاطب:**  \n\n> 🟢 BTC: **$62,932.29** (+1.11%)\n> 🟢 ETH: **$1,754.66** (+0.82%)\n> 🟢 BNB: **$572.61** (+1.84%)\n> 🟢 XRP: **$1.10** (+1.48%)\n> 🟢 SOL: **$78.19** (+1.24%)\n> 🟢 TRX: **$0.33** (+0.94%)\n> 🟢 DOGE: **$0.07** (+2.13%)\n> 🟢 HYPE: **$68.19** (+0.54%)\n> 🟢 NEAR: **$1.93** (+2.10%)\n> 🟢 AVAX: **$6.75** (+6.37%)\n> 🟢 ASTER: **$0.62** (+1.83%)\n> 🟢 ONDO: **$0.32** (+0.89%)\n> 🟢 AAVE: **$88.50** (+1.38%)\n  \n**🚮قیمت ارزهای تلگرامی:**  \n\n> 🟢 GRAM (TON): **$1.588780** (+1.23%)\n> 🟢 NOT: **$0.000388** (+1.87%)\n> 🟢 DOGS: **$0.000039** (+1.88%)\n> 🟢 HMSTR: **$0.000201** (+1.16%)\n> 🔴 EVAA: **$2.454416** (-16.19%)\n> 🟢 X: **$0.000011** (+0.09%)\n> 🟢 MAJOR: **$0.034108** (+3.24%)\n> 🟢 PX: **$0.014238** (+7.75%)\n> 🟢 STON: **$0.545164** (+0.14%)\n> 🔴 REDO: **$0.063959** (-1.58%)\n> 🟢 UTYA: **$0.024930** (+5.32%)\n> 🔴 DUST: **$0.000152** (-3.84%)\n> 🟢 TONNEL: **$0.625406** (+0.51%)\n> 🔴 FISH: **$0.005422** (+0.00%)\n  \n**🟡قیمت طلا و نقره:**  \n\n> 🌍 انس طلا (دلار): **4,123.20$**\n> 🌍 انس نقره (دلار): **59.72$**\n> 💰 طلا ۱۸ عیار (هر گرم): **17,983,000** تومان\n> 💰 طلا ۲۴ عیار (هر گرم): **23,977,200** تومان\n> 🥇 سکه گرمی: **27,000,000** تومان\n> 🥇 ربع سکه: **54,500,000** تومان\n> 🥇 نیم سکه: **95,150,000** تومان\n> 🥇 سکه بهار آزادی: **177,035,000** تومان\n> 🥇 سکه امامی: **182,990,000** تومان\n> 🥈 گرم نقره ۹۹۹: **361,350** تومان\n  \n**🛢قیمت نفت:**  \n\n> 🇺🇸 نفت WTI (تگزاس): **72.9$** (-2%)\n> 🇬🇧 نفت Brent (برنت): **77.4$** (-2%)\n  \n[#دلار](?q=%23%D8%AF%D9%84%D8%A7%D8%B1) [#طلا](?q=%23%D8%B7%D9%84%D8%A7) [#نفت](?q=%23%D9%86%D9%81%D8%AA)  \n\n> 🫀نبض بازار در دستان شماست...\n> [@PriceNerd](https://t.me/PriceNerd)\n",
  "timestamp": "12:19",
  "photo_url": null,
  "photo_count": 0,
  "video_url": null,
  "video_thumb_url": null,
  "audio_url": null,
  "document_url": null,
  "document_filename": null,
  "document_description": null,
  "telegram_post_link": null,
  "downloaded_media": [],
  "fetched_at": "2026-07-09T09:02:35Z"
}