{
  "message_id": "306998",
  "channel": "VahidHeadline",
  "channel_url": "https://t.me/s/VahidHeadline",
  "content": "🔺تیراندازی مرگبار در آلمان؛ افزایش نگرانی‌ها درباره تهدیدهای امنیتی جمهوری اسلامی در اروپا  \n  \n▪️در حالی که مقام‌های اروپایی طی هفته‌های اخیر بار دیگر نسبت به فعالیت‌های منتسب به نهادهای امنیتی جمهوری اسلامی در کشورهای غربی هشدار داده‌اند، روز دوشنبه ۸ تیر یک تیراندازی مرگبار در شمال آلمان دست‌کم پنج کشته بر جای گذاشت.  \n  \n⬇️ بیشتر بخوانید:  \n  \n[ir](https://ir.voanews.com/a/five-people-shot-dead-northern-germany/8166001.html/?nocach=1)  \n[‌](https://t.me/farsivoa/222215)[🇺🇸](https://fa.wikipedia.org/wiki/%D8%B5%D8%AF%D8%A7%DB%8C_%D8%A2%D9%85%D8%B1%DB%8C%DA%A9%D8%A7) *FarsiVOA*  \n  \n🤖 [@VahidHeadline](https://t.me/VahidHeadline)",
  "timestamp": "18:22",
  "photo_url": null,
  "photo_count": 0,
  "video_url": null,
  "video_thumb_url": null,
  "audio_url": null,
  "document_url": null,
  "document_filename": null,
  "document_description": null,
  "telegram_post_link": null,
  "downloaded_media": [],
  "fetched_at": "2026-06-29T15:01:31Z"
}